{
    "database_version": "0.3",
    "last_updated": "2025-09-17",
    "Consumables": {
        "Consumables": {
            "Paper": {
                "flags": [
                    "Market",
                    "Secure",
                    "Store",
                    "Events",
                    "P2P"
                ],
                "tier": 4,
                "value": 240,
                "variants": []
            },
            "PunchedCard": {
                "flags": [
                    "Market",
                    "Secure",
                    "Store",
                    "Events",
                    "P2P"
                ],
                "tier": 4,
                "value": 240,
                "variants": []
            },
            "GiftWrapPaper": {
                "flags": [
                    "Market",
                    "Secure",
                    "Store",
                    "Events",
                    "P2P"
                ],
                "tier": 4,
                "value": 240,
                "variants": []
            },
            "DuctTape": {
                "flags": [
                    "Market",
                    "Secure",
                    "Store",
                    "Events",
                    "P2P"
                ],
                "tier": 4,
                "value": 240,
                "variants": []
            },
            "Rag": {
                "flags": [
                    "Market",
                    "Secure",
                    "Store",
                    "Events",
                    "P2P"
                ],
                "tier": 4,
                "value": 240,
                "variants": []
            },
            "BurlapStrip": {
                "flags": [
                    "Market",
                    "Secure",
                    "Store",
                    "Events",
                    "P2P"
                ],
                "tier": 4,
                "value": 240,
                "variants": []
            },
            "Stone": {
                "flags": [
                    "Market",
                    "Secure",
                    "Store",
                    "Events",
                    "P2P"
                ],
                "tier": 4,
                "value": 240,
                "variants": []
            },
            "SmallStone": {
                "flags": [
                    "Market",
                    "Secure",
                    "Store",
                    "Events",
                    "P2P"
                ],
                "tier": 4,
                "value": 240,
                "variants": []
            },
            "Firewood": {
                "flags": [
                    "Market",
                    "Secure",
                    "Store",
                    "Events",
                    "P2P"
                ],
                "tier": 4,
                "value": 240,
                "variants": []
            },
            "Battery9V": {
                "flags": [
                    "Market",
                    "Secure",
                    "Store",
                    "Events",
                    "P2P"
                ],
                "tier": 4,
                "value": 240,
                "variants": []
            },
            "LargeGasCanister": {
                "flags": [
                    "Market",
                    "Secure",
                    "Store",
                    "Events",
                    "P2P"
                ],
                "tier": 4,
                "value": 240,
                "variants": []
            },
            "MediumGasCanister": {
                "flags": [
                    "Market",
                    "Secure",
                    "Store",
                    "Events",
                    "P2P"
                ],
                "tier": 4,
                "value": 240,
                "variants": []
            },
            "SmallGasCanister": {
                "flags": [
                    "Market",
                    "Secure",
                    "Store",
                    "Events",
                    "P2P"
                ],
                "tier": 4,
                "value": 240,
                "variants": []
            },
            "ButaneCanister": {
                "flags": [
                    "Market",
                    "Secure",
                    "Store",
                    "Events",
                    "P2P"
                ],
                "tier": 4,
                "value": 240,
                "variants": []
            },
            "Spraycan_Black": {
                "flags": [
                    "Market",
                    "Secure",
                    "Store",
                    "Events",
                    "P2P"
                ],
                "tier": 4,
                "value": 240,
                "variants": []
            },
            "Spraycan_Green": {
                "flags": [
                    "Market",
                    "Secure",
                    "Store",
                    "Events",
                    "P2P"
                ],
                "tier": 4,
                "value": 240,
                "variants": []
            },
            "Matchbox": {
                "flags": [
                    "Market",
                    "Secure",
                    "Store",
                    "Events",
                    "P2P"
                ],
                "tier": 4,
                "value": 240,
                "variants": []
            },
            "NailBox": {
                "flags": [
                    "Market",
                    "Secure",
                    "Store",
                    "Events",
                    "P2P"
                ],
                "tier": 4,
                "value": 240,
                "variants": []
            },
            "Roadflare": {
                "flags": [
                    "Market",
                    "Secure",
                    "Store",
                    "Events",
                    "P2P"
                ],
                "tier": 4,
                "value": 240,
                "variants": []
            },
            "Chemlight_White": {
                "flags": [
                    "Market",
                    "Secure",
                    "Store",
                    "Events",
                    "P2P"
                ],
                "tier": 4,
                "value": 240,
                "variants": []
            },
            "Chemlight_Red": {
                "flags": [
                    "Market",
                    "Secure",
                    "Store",
                    "Events",
                    "P2P"
                ],
                "tier": 4,
                "value": 240,
                "variants": []
            },
            "Chemlight_Green": {
                "flags": [
                    "Market",
                    "Secure",
                    "Store",
                    "Events",
                    "P2P"
                ],
                "tier": 4,
                "value": 240,
                "variants": []
            },
            "Chemlight_Blue": {
                "flags": [
                    "Market",
                    "Secure",
                    "Store",
                    "Events",
                    "P2P"
                ],
                "tier": 4,
                "value": 240,
                "variants": []
            },
            "Chemlight_Yellow": {
                "flags": [
                    "Market",
                    "Secure",
                    "Store",
                    "Events",
                    "P2P"
                ],
                "tier": 4,
                "value": 240,
                "variants": []
            },
            "Pelt_Base": {
                "flags": [
                    "Market",
                    "Secure",
                    "Store",
                    "Events",
                    "P2P"
                ],
                "tier": 4,
                "value": 240,
                "variants": []
            },
            "WildboarPelt": {
                "flags": [
                    "Market",
                    "Secure",
                    "Store",
                    "Events",
                    "P2P"
                ],
                "tier": 4,
                "value": 240,
                "variants": []
            },
            "RabbitPelt": {
                "flags": [
                    "Market",
                    "Secure",
                    "Store",
                    "Events",
                    "P2P"
                ],
                "tier": 4,
                "value": 240,
                "variants": []
            },
            "CowPelt": {
                "flags": [
                    "Market",
                    "Secure",
                    "Store",
                    "Events",
                    "P2P"
                ],
                "tier": 4,
                "value": 240,
                "variants": []
            },
            "PigPelt": {
                "flags": [
                    "Market",
                    "Secure",
                    "Store",
                    "Events",
                    "P2P"
                ],
                "tier": 4,
                "value": 240,
                "variants": []
            },
            "DeerPelt": {
                "flags": [
                    "Market",
                    "Secure",
                    "Store",
                    "Events",
                    "P2P"
                ],
                "tier": 4,
                "value": 240,
                "variants": []
            },
            "ReindeerPelt": {
                "flags": [
                    "Market",
                    "Secure",
                    "Store",
                    "Events",
                    "P2P"
                ],
                "tier": 4,
                "value": 240,
                "variants": []
            },
            "GoatPelt": {
                "flags": [
                    "Market",
                    "Secure",
                    "Store",
                    "Events",
                    "P2P"
                ],
                "tier": 4,
                "value": 240,
                "variants": []
            },
            "BearPelt": {
                "flags": [
                    "Market",
                    "Secure",
                    "Store",
                    "Events",
                    "P2P"
                ],
                "tier": 4,
                "value": 240,
                "variants": []
            },
            "WolfPelt": {
                "flags": [
                    "Market",
                    "Secure",
                    "Store",
                    "Events",
                    "P2P"
                ],
                "tier": 4,
                "value": 240,
                "variants": []
            },
            "SheepPelt": {
                "flags": [
                    "Market",
                    "Secure",
                    "Store",
                    "Events",
                    "P2P"
                ],
                "tier": 4,
                "value": 240,
                "variants": []
            },
            "MouflonPelt": {
                "flags": [
                    "Market",
                    "Secure",
                    "Store",
                    "Events",
                    "P2P"
                ],
                "tier": 4,
                "value": 240,
                "variants": []
            },
            "FoxPelt": {
                "flags": [
                    "Market",
                    "Secure",
                    "Store",
                    "Events",
                    "P2P"
                ],
                "tier": 4,
                "value": 240,
                "variants": []
            },
            "TannedLeather": {
                "flags": [
                    "Market",
                    "Secure",
                    "Store",
                    "Events",
                    "P2P"
                ],
                "tier": 4,
                "value": 240,
                "variants": []
            },
            "Hook": {
                "flags": [
                    "Market",
                    "Secure",
                    "Store",
                    "Events",
                    "P2P"
                ],
                "tier": 4,
                "value": 240,
                "variants": []
            },
            "BoneHook": {
                "flags": [
                    "Market",
                    "Secure",
                    "Store",
                    "Events",
                    "P2P"
                ],
                "tier": 4,
                "value": 240,
                "variants": []
            },
            "WoodenHook": {
                "flags": [
                    "Market",
                    "Secure",
                    "Store",
                    "Events",
                    "P2P"
                ],
                "tier": 4,
                "value": 240,
                "variants": []
            },
            "Bark_Oak": {
                "flags": [
                    "Market",
                    "Secure",
                    "Store",
                    "Events",
                    "P2P"
                ],
                "tier": 4,
                "value": 240,
                "variants": []
            },
            "Bark_Birch": {
                "flags": [
                    "Market",
                    "Secure",
                    "Store",
                    "Events",
                    "P2P"
                ],
                "tier": 4,
                "value": 240,
                "variants": []
            },
            "Nail": {
                "flags": [
                    "Market",
                    "Secure",
                    "Store",
                    "Events",
                    "P2P"
                ],
                "tier": 4,
                "value": 240,
                "variants": []
            },
            "Bone": {
                "flags": [
                    "Market",
                    "Secure",
                    "Store",
                    "Events",
                    "P2P"
                ],
                "tier": 4,
                "value": 240,
                "variants": []
            },
            "Bait": {
                "flags": [
                    "Market",
                    "Secure",
                    "Store",
                    "Events",
                    "P2P"
                ],
                "tier": 4,
                "value": 240,
                "variants": []
            },
            "BoneBait": {
                "flags": [
                    "Market",
                    "Secure",
                    "Store",
                    "Events",
                    "P2P"
                ],
                "tier": 4,
                "value": 240,
                "variants": []
            },
            "Jig": {
                "flags": [
                    "Market",
                    "Secure",
                    "Store",
                    "Events",
                    "P2P"
                ],
                "tier": 4,
                "value": 240,
                "variants": []
            },
            "GardenLime": {
                "flags": [
                    "Market",
                    "Secure",
                    "Store",
                    "Events",
                    "P2P"
                ],
                "tier": 4,
                "value": 240,
                "variants": []
            },
            "Netting": {
                "flags": [
                    "Market",
                    "Secure",
                    "Store",
                    "Events",
                    "P2P"
                ],
                "tier": 4,
                "value": 240,
                "variants": []
            },
            "WoodenPlank": {
                "flags": [
                    "Market",
                    "Secure",
                    "Store",
                    "Events",
                    "P2P"
                ],
                "tier": 4,
                "value": 240,
                "variants": []
            },
            "PileOfWoodenPlanks": {
                "flags": [
                    "Market",
                    "Secure",
                    "Store",
                    "Events",
                    "P2P"
                ],
                "tier": 4,
                "value": 240,
                "variants": []
            },
            "MetalPlate": {
                "flags": [
                    "Market",
                    "Secure",
                    "Store",
                    "Events",
                    "P2P"
                ],
                "tier": 4,
                "value": 240,
                "variants": []
            },
            "WoodenLog": {
                "flags": [
                    "Market",
                    "Secure",
                    "Store",
                    "Events",
                    "P2P"
                ],
                "tier": 4,
                "value": 240,
                "variants": []
            },
            "EasterEgg": {
                "flags": [
                    "Market",
                    "Secure",
                    "Store",
                    "Events",
                    "P2P"
                ],
                "tier": 4,
                "value": 240,
                "variants": []
            },
            "GasMask_Filter": {
                "flags": [
                    "Market",
                    "Secure",
                    "Store",
                    "Events",
                    "P2P"
                ],
                "tier": 4,
                "value": 240,
                "variants": []
            }
        }
    },
    "CategoryDefaults": {
        "Consumables": {
            "restock": 1800,
            "cost": 240
        },
        "Lights": {
            "restock": 1800,
            "cost": 240
        }
    },
    "Categories": {
        "Consumables": {
            "Bait": {
                "cost": 240,
                "flags": {
                    "Events": true,
                    "Market": true,
                    "P2P": true,
                    "Secure": true,
                    "Store": true,
                    "count_in_map": 1,
                    "deloot": 0
                },
                "lifetime": 14400,
                "min": 0,
                "nominal": 0,
                "quantmax": -1,
                "quantmin": -1,
                "restock": 1800,
                "tier": 4,
                "value": 240,
                "variants": {}
            },
            "Bark_Birch": {
                "cost": 240,
                "flags": {
                    "Events": true,
                    "Market": true,
                    "P2P": true,
                    "Secure": true,
                    "Store": true,
                    "count_in_map": 1,
                    "deloot": 0
                },
                "lifetime": 14400,
                "min": 0,
                "nominal": 0,
                "quantmax": -1,
                "quantmin": -1,
                "restock": 1800,
                "tier": 4,
                "value": 240,
                "variants": {}
            },
            "Bark_Oak": {
                "cost": 240,
                "flags": {
                    "Events": true,
                    "Market": true,
                    "P2P": true,
                    "Secure": true,
                    "Store": true,
                    "count_in_map": 1,
                    "deloot": 0
                },
                "lifetime": 14400,
                "min": 0,
                "nominal": 0,
                "quantmax": -1,
                "quantmin": -1,
                "restock": 1800,
                "tier": 4,
                "value": 240,
                "variants": {}
            },
            "Battery9V": {
                "cost": 240,
                "flags": {
                    "Events": true,
                    "Market": true,
                    "P2P": true,
                    "Secure": true,
                    "Store": true,
                    "count_in_map": 1,
                    "deloot": 0
                },
                "lifetime": 14400,
                "min": 0,
                "nominal": 0,
                "quantmax": -1,
                "quantmin": -1,
                "restock": 1800,
                "tier": 4,
                "value": 240,
                "variants": {}
            },
            "BearPelt": {
                "cost": 240,
                "flags": {
                    "Events": true,
                    "Market": true,
                    "P2P": true,
                    "Secure": true,
                    "Store": true,
                    "count_in_map": 1,
                    "deloot": 0
                },
                "lifetime": 14400,
                "min": 0,
                "nominal": 0,
                "quantmax": -1,
                "quantmin": -1,
                "restock": 1800,
                "tier": 4,
                "value": 240,
                "variants": {}
            },
            "Bone": {
                "cost": 240,
                "flags": {
                    "Events": true,
                    "Market": true,
                    "P2P": true,
                    "Secure": true,
                    "Store": true,
                    "count_in_map": 1,
                    "deloot": 0
                },
                "lifetime": 14400,
                "min": 0,
                "nominal": 0,
                "quantmax": -1,
                "quantmin": -1,
                "restock": 1800,
                "tier": 4,
                "value": 240,
                "variants": {}
            },
            "BoneBait": {
                "cost": 240,
                "flags": {
                    "Events": true,
                    "Market": true,
                    "P2P": true,
                    "Secure": true,
                    "Store": true,
                    "count_in_map": 1,
                    "deloot": 0
                },
                "lifetime": 14400,
                "min": 0,
                "nominal": 0,
                "quantmax": -1,
                "quantmin": -1,
                "restock": 1800,
                "tier": 4,
                "value": 240,
                "variants": {}
            },
            "BoneHook": {
                "cost": 240,
                "flags": {
                    "Events": true,
                    "Market": true,
                    "P2P": true,
                    "Secure": true,
                    "Store": true,
                    "count_in_map": 1,
                    "deloot": 0
                },
                "lifetime": 14400,
                "min": 0,
                "nominal": 0,
                "quantmax": -1,
                "quantmin": -1,
                "restock": 1800,
                "tier": 4,
                "value": 240,
                "variants": {}
            },
            "BurlapStrip": {
                "cost": 240,
                "flags": {
                    "Events": true,
                    "Market": true,
                    "P2P": true,
                    "Secure": true,
                    "Store": true,
                    "count_in_map": 1,
                    "deloot": 0
                },
                "lifetime": 14400,
                "min": 0,
                "nominal": 0,
                "quantmax": -1,
                "quantmin": -1,
                "restock": 1800,
                "tier": 4,
                "value": 240,
                "variants": {}
            },
            "ButaneCanister": {
                "cost": 240,
                "flags": {
                    "Events": true,
                    "Market": true,
                    "P2P": true,
                    "Secure": true,
                    "Store": true,
                    "count_in_map": 1,
                    "deloot": 0
                },
                "lifetime": 14400,
                "min": 0,
                "nominal": 0,
                "quantmax": -1,
                "quantmin": -1,
                "restock": 1800,
                "tier": 4,
                "value": 240,
                "variants": {}
            },
            "CowPelt": {
                "cost": 240,
                "flags": {
                    "Events": true,
                    "Market": true,
                    "P2P": true,
                    "Secure": true,
                    "Store": true,
                    "count_in_map": 1,
                    "deloot": 0
                },
                "lifetime": 14400,
                "min": 0,
                "nominal": 0,
                "quantmax": -1,
                "quantmin": -1,
                "restock": 1800,
                "tier": 4,
                "value": 240,
                "variants": {}
            },
            "DeerPelt": {
                "cost": 240,
                "flags": {
                    "Events": true,
                    "Market": true,
                    "P2P": true,
                    "Secure": true,
                    "Store": true,
                    "count_in_map": 1,
                    "deloot": 0
                },
                "lifetime": 14400,
                "min": 0,
                "nominal": 0,
                "quantmax": -1,
                "quantmin": -1,
                "restock": 1800,
                "tier": 4,
                "value": 240,
                "variants": {}
            },
            "DuctTape": {
                "cost": 240,
                "flags": {
                    "Events": true,
                    "Market": true,
                    "P2P": true,
                    "Secure": true,
                    "Store": true,
                    "count_in_map": 1,
                    "deloot": 0
                },
                "lifetime": 14400,
                "min": 0,
                "nominal": 0,
                "quantmax": -1,
                "quantmin": -1,
                "restock": 1800,
                "tier": 4,
                "value": 240,
                "variants": {}
            },
            "EasterEgg": {
                "cost": 240,
                "flags": {
                    "Events": true,
                    "Market": true,
                    "P2P": true,
                    "Secure": true,
                    "Store": true,
                    "count_in_map": 1,
                    "deloot": 0
                },
                "lifetime": 14400,
                "min": 0,
                "nominal": 0,
                "quantmax": -1,
                "quantmin": -1,
                "restock": 1800,
                "tier": 4,
                "value": 240,
                "variants": {}
            },
            "Firewood": {
                "cost": 240,
                "flags": {
                    "Events": true,
                    "Market": true,
                    "P2P": true,
                    "Secure": true,
                    "Store": true,
                    "count_in_map": 1,
                    "deloot": 0
                },
                "lifetime": 14400,
                "min": 0,
                "nominal": 0,
                "quantmax": -1,
                "quantmin": -1,
                "restock": 1800,
                "tier": 4,
                "value": 240,
                "variants": {}
            },
            "FoxPelt": {
                "cost": 240,
                "flags": {
                    "Events": true,
                    "Market": true,
                    "P2P": true,
                    "Secure": true,
                    "Store": true,
                    "count_in_map": 1,
                    "deloot": 0
                },
                "lifetime": 14400,
                "min": 0,
                "nominal": 0,
                "quantmax": -1,
                "quantmin": -1,
                "restock": 1800,
                "tier": 4,
                "value": 240,
                "variants": {}
            },
            "GardenLime": {
                "cost": 240,
                "flags": {
                    "Events": true,
                    "Market": true,
                    "P2P": true,
                    "Secure": true,
                    "Store": true,
                    "count_in_map": 1,
                    "deloot": 0
                },
                "lifetime": 14400,
                "min": 0,
                "nominal": 0,
                "quantmax": -1,
                "quantmin": -1,
                "restock": 1800,
                "tier": 4,
                "value": 240,
                "variants": {}
            },
            "GasMask_Filter": {
                "cost": 240,
                "flags": {
                    "Events": true,
                    "Market": true,
                    "P2P": true,
                    "Secure": true,
                    "Store": true,
                    "count_in_map": 1,
                    "deloot": 0
                },
                "lifetime": 14400,
                "min": 0,
                "nominal": 0,
                "quantmax": -1,
                "quantmin": -1,
                "restock": 1800,
                "tier": 4,
                "value": 240,
                "variants": {}
            },
            "GiftWrapPaper": {
                "cost": 240,
                "flags": {
                    "Events": true,
                    "Market": true,
                    "P2P": true,
                    "Secure": true,
                    "Store": true,
                    "count_in_map": 1,
                    "deloot": 0
                },
                "lifetime": 14400,
                "min": 0,
                "nominal": 0,
                "quantmax": -1,
                "quantmin": -1,
                "restock": 1800,
                "tier": 4,
                "value": 240,
                "variants": {}
            },
            "GoatPelt": {
                "cost": 240,
                "flags": {
                    "Events": true,
                    "Market": true,
                    "P2P": true,
                    "Secure": true,
                    "Store": true,
                    "count_in_map": 1,
                    "deloot": 0
                },
                "lifetime": 14400,
                "min": 0,
                "nominal": 0,
                "quantmax": -1,
                "quantmin": -1,
                "restock": 1800,
                "tier": 4,
                "value": 240,
                "variants": {}
            },
            "Hook": {
                "cost": 240,
                "flags": {
                    "Events": true,
                    "Market": true,
                    "P2P": true,
                    "Secure": true,
                    "Store": true,
                    "count_in_map": 1,
                    "deloot": 0
                },
                "lifetime": 14400,
                "min": 0,
                "nominal": 0,
                "quantmax": -1,
                "quantmin": -1,
                "restock": 1800,
                "tier": 4,
                "value": 240,
                "variants": {}
            },
            "Jig": {
                "cost": 240,
                "flags": {
                    "Events": true,
                    "Market": true,
                    "P2P": true,
                    "Secure": true,
                    "Store": true,
                    "count_in_map": 1,
                    "deloot": 0
                },
                "lifetime": 14400,
                "min": 0,
                "nominal": 0,
                "quantmax": -1,
                "quantmin": -1,
                "restock": 1800,
                "tier": 4,
                "value": 240,
                "variants": {}
            },
            "LargeGasCanister": {
                "cost": 240,
                "flags": {
                    "Events": true,
                    "Market": true,
                    "P2P": true,
                    "Secure": true,
                    "Store": true,
                    "count_in_map": 1,
                    "deloot": 0
                },
                "lifetime": 14400,
                "min": 0,
                "nominal": 0,
                "quantmax": -1,
                "quantmin": -1,
                "restock": 1800,
                "tier": 4,
                "value": 240,
                "variants": {}
            },
            "Matchbox": {
                "cost": 240,
                "flags": {
                    "Events": true,
                    "Market": true,
                    "P2P": true,
                    "Secure": true,
                    "Store": true,
                    "count_in_map": 1,
                    "deloot": 0
                },
                "lifetime": 14400,
                "min": 0,
                "nominal": 0,
                "quantmax": -1,
                "quantmin": -1,
                "restock": 1800,
                "tier": 4,
                "value": 240,
                "variants": {}
            },
            "MediumGasCanister": {
                "cost": 240,
                "flags": {
                    "Events": true,
                    "Market": true,
                    "P2P": true,
                    "Secure": true,
                    "Store": true,
                    "count_in_map": 1,
                    "deloot": 0
                },
                "lifetime": 14400,
                "min": 0,
                "nominal": 0,
                "quantmax": -1,
                "quantmin": -1,
                "restock": 1800,
                "tier": 4,
                "value": 240,
                "variants": {}
            },
            "MetalPlate": {
                "cost": 240,
                "flags": {
                    "Events": true,
                    "Market": true,
                    "P2P": true,
                    "Secure": true,
                    "Store": true,
                    "count_in_map": 1,
                    "deloot": 0
                },
                "lifetime": 14400,
                "min": 0,
                "nominal": 0,
                "quantmax": -1,
                "quantmin": -1,
                "restock": 1800,
                "tier": 4,
                "value": 240,
                "variants": {}
            },
            "MouflonPelt": {
                "cost": 240,
                "flags": {
                    "Events": true,
                    "Market": true,
                    "P2P": true,
                    "Secure": true,
                    "Store": true,
                    "count_in_map": 1,
                    "deloot": 0
                },
                "lifetime": 14400,
                "min": 0,
                "nominal": 0,
                "quantmax": -1,
                "quantmin": -1,
                "restock": 1800,
                "tier": 4,
                "value": 240,
                "variants": {}
            },
            "Nail": {
                "cost": 240,
                "flags": {
                    "Events": true,
                    "Market": true,
                    "P2P": true,
                    "Secure": true,
                    "Store": true,
                    "count_in_map": 1,
                    "deloot": 0
                },
                "lifetime": 14400,
                "min": 0,
                "nominal": 0,
                "quantmax": -1,
                "quantmin": -1,
                "restock": 1800,
                "tier": 4,
                "value": 240,
                "variants": {}
            },
            "NailBox": {
                "cost": 240,
                "flags": {
                    "Events": true,
                    "Market": true,
                    "P2P": true,
                    "Secure": true,
                    "Store": true,
                    "count_in_map": 1,
                    "deloot": 0
                },
                "lifetime": 14400,
                "min": 0,
                "nominal": 0,
                "quantmax": -1,
                "quantmin": -1,
                "restock": 1800,
                "tier": 4,
                "value": 240,
                "variants": {}
            },
            "Netting": {
                "cost": 240,
                "flags": {
                    "Events": true,
                    "Market": true,
                    "P2P": true,
                    "Secure": true,
                    "Store": true,
                    "count_in_map": 1,
                    "deloot": 0
                },
                "lifetime": 14400,
                "min": 0,
                "nominal": 0,
                "quantmax": -1,
                "quantmin": -1,
                "restock": 1800,
                "tier": 4,
                "value": 240,
                "variants": {}
            },
            "Paper": {
                "cost": 240,
                "flags": {
                    "Events": true,
                    "Market": true,
                    "P2P": true,
                    "Secure": true,
                    "Store": true,
                    "count_in_map": 1,
                    "deloot": 0
                },
                "lifetime": 14400,
                "min": 0,
                "nominal": 0,
                "quantmax": -1,
                "quantmin": -1,
                "restock": 1800,
                "tier": 4,
                "value": 240,
                "variants": {}
            },
            "Pelt_Base": {
                "cost": 240,
                "flags": {
                    "Events": true,
                    "Market": true,
                    "P2P": true,
                    "Secure": true,
                    "Store": true,
                    "count_in_map": 1,
                    "deloot": 0
                },
                "lifetime": 14400,
                "min": 0,
                "nominal": 0,
                "quantmax": -1,
                "quantmin": -1,
                "restock": 1800,
                "tier": 4,
                "value": 240,
                "variants": {}
            },
            "PigPelt": {
                "cost": 240,
                "flags": {
                    "Events": true,
                    "Market": true,
                    "P2P": true,
                    "Secure": true,
                    "Store": true,
                    "count_in_map": 1,
                    "deloot": 0
                },
                "lifetime": 14400,
                "min": 0,
                "nominal": 0,
                "quantmax": -1,
                "quantmin": -1,
                "restock": 1800,
                "tier": 4,
                "value": 240,
                "variants": {}
            },
            "PileOfWoodenPlanks": {
                "cost": 240,
                "flags": {
                    "Events": true,
                    "Market": true,
                    "P2P": true,
                    "Secure": true,
                    "Store": true,
                    "count_in_map": 1,
                    "deloot": 0
                },
                "lifetime": 14400,
                "min": 0,
                "nominal": 0,
                "quantmax": -1,
                "quantmin": -1,
                "restock": 1800,
                "tier": 4,
                "value": 240,
                "variants": {}
            },
            "PunchedCard": {
                "cost": 240,
                "flags": {
                    "Events": true,
                    "Market": true,
                    "P2P": true,
                    "Secure": true,
                    "Store": true,
                    "count_in_map": 1,
                    "deloot": 0
                },
                "lifetime": 14400,
                "min": 0,
                "nominal": 0,
                "quantmax": -1,
                "quantmin": -1,
                "restock": 1800,
                "tier": 4,
                "value": 240,
                "variants": {}
            },
            "RabbitPelt": {
                "cost": 240,
                "flags": {
                    "Events": true,
                    "Market": true,
                    "P2P": true,
                    "Secure": true,
                    "Store": true,
                    "count_in_map": 1,
                    "deloot": 0
                },
                "lifetime": 14400,
                "min": 0,
                "nominal": 0,
                "quantmax": -1,
                "quantmin": -1,
                "restock": 1800,
                "tier": 4,
                "value": 240,
                "variants": {}
            },
            "Rag": {
                "cost": 240,
                "flags": {
                    "Events": true,
                    "Market": true,
                    "P2P": true,
                    "Secure": true,
                    "Store": true,
                    "count_in_map": 1,
                    "deloot": 0
                },
                "lifetime": 14400,
                "min": 0,
                "nominal": 0,
                "quantmax": -1,
                "quantmin": -1,
                "restock": 1800,
                "tier": 4,
                "value": 240,
                "variants": {}
            },
            "ReindeerPelt": {
                "cost": 240,
                "flags": {
                    "Events": true,
                    "Market": true,
                    "P2P": true,
                    "Secure": true,
                    "Store": true,
                    "count_in_map": 1,
                    "deloot": 0
                },
                "lifetime": 14400,
                "min": 0,
                "nominal": 0,
                "quantmax": -1,
                "quantmin": -1,
                "restock": 1800,
                "tier": 4,
                "value": 240,
                "variants": {}
            },
            "Roadflare": {
                "cost": 240,
                "flags": {
                    "Events": true,
                    "Market": true,
                    "P2P": true,
                    "Secure": true,
                    "Store": true,
                    "count_in_map": 1,
                    "deloot": 0
                },
                "lifetime": 14400,
                "min": 0,
                "nominal": 0,
                "quantmax": -1,
                "quantmin": -1,
                "restock": 1800,
                "tier": 4,
                "value": 240,
                "variants": {}
            },
            "SheepPelt": {
                "cost": 240,
                "flags": {
                    "Events": true,
                    "Market": true,
                    "P2P": true,
                    "Secure": true,
                    "Store": true,
                    "count_in_map": 1,
                    "deloot": 0
                },
                "lifetime": 14400,
                "min": 0,
                "nominal": 0,
                "quantmax": -1,
                "quantmin": -1,
                "restock": 1800,
                "tier": 4,
                "value": 240,
                "variants": {}
            },
            "SmallGasCanister": {
                "cost": 240,
                "flags": {
                    "Events": true,
                    "Market": true,
                    "P2P": true,
                    "Secure": true,
                    "Store": true,
                    "count_in_map": 1,
                    "deloot": 0
                },
                "lifetime": 14400,
                "min": 0,
                "nominal": 0,
                "quantmax": -1,
                "quantmin": -1,
                "restock": 1800,
                "tier": 4,
                "value": 240,
                "variants": {}
            },
            "SmallStone": {
                "cost": 240,
                "flags": {
                    "Events": true,
                    "Market": true,
                    "P2P": true,
                    "Secure": true,
                    "Store": true,
                    "count_in_map": 1,
                    "deloot": 0
                },
                "lifetime": 14400,
                "min": 0,
                "nominal": 0,
                "quantmax": -1,
                "quantmin": -1,
                "restock": 1800,
                "tier": 4,
                "value": 240,
                "variants": {}
            },
            "Spraycan_Black": {
                "cost": 240,
                "flags": {
                    "Events": true,
                    "Market": true,
                    "P2P": true,
                    "Secure": true,
                    "Store": true,
                    "count_in_map": 1,
                    "deloot": 0
                },
                "lifetime": 14400,
                "min": 0,
                "nominal": 0,
                "quantmax": -1,
                "quantmin": -1,
                "restock": 1800,
                "tier": 4,
                "value": 240,
                "variants": {
                    "Spraycan_Green": {}
                }
            },
            "Stone": {
                "cost": 240,
                "flags": {
                    "Events": true,
                    "Market": true,
                    "P2P": true,
                    "Secure": true,
                    "Store": true,
                    "count_in_map": 1,
                    "deloot": 0
                },
                "lifetime": 14400,
                "min": 0,
                "nominal": 0,
                "quantmax": -1,
                "quantmin": -1,
                "restock": 1800,
                "tier": 4,
                "value": 240,
                "variants": {}
            },
            "TannedLeather": {
                "cost": 240,
                "flags": {
                    "Events": true,
                    "Market": true,
                    "P2P": true,
                    "Secure": true,
                    "Store": true,
                    "count_in_map": 1,
                    "deloot": 0
                },
                "lifetime": 14400,
                "min": 0,
                "nominal": 0,
                "quantmax": -1,
                "quantmin": -1,
                "restock": 1800,
                "tier": 4,
                "value": 240,
                "variants": {}
            },
            "WildboarPelt": {
                "cost": 240,
                "flags": {
                    "Events": true,
                    "Market": true,
                    "P2P": true,
                    "Secure": true,
                    "Store": true,
                    "count_in_map": 1,
                    "deloot": 0
                },
                "lifetime": 14400,
                "min": 0,
                "nominal": 0,
                "quantmax": -1,
                "quantmin": -1,
                "restock": 1800,
                "tier": 4,
                "value": 240,
                "variants": {}
            },
            "WolfPelt": {
                "cost": 240,
                "flags": {
                    "Events": true,
                    "Market": true,
                    "P2P": true,
                    "Secure": true,
                    "Store": true,
                    "count_in_map": 1,
                    "deloot": 0
                },
                "lifetime": 14400,
                "min": 0,
                "nominal": 0,
                "quantmax": -1,
                "quantmin": -1,
                "restock": 1800,
                "tier": 4,
                "value": 240,
                "variants": {}
            },
            "WoodenHook": {
                "cost": 240,
                "flags": {
                    "Events": true,
                    "Market": true,
                    "P2P": true,
                    "Secure": true,
                    "Store": true,
                    "count_in_map": 1,
                    "deloot": 0
                },
                "lifetime": 14400,
                "min": 0,
                "nominal": 0,
                "quantmax": -1,
                "quantmin": -1,
                "restock": 1800,
                "tier": 4,
                "value": 240,
                "variants": {}
            },
            "WoodenLog": {
                "cost": 240,
                "flags": {
                    "Events": true,
                    "Market": true,
                    "P2P": true,
                    "Secure": true,
                    "Store": true,
                    "count_in_map": 1,
                    "deloot": 0
                },
                "lifetime": 14400,
                "min": 0,
                "nominal": 0,
                "quantmax": -1,
                "quantmin": -1,
                "restock": 1800,
                "tier": 4,
                "value": 240,
                "variants": {}
            },
            "WoodenPlank": {
                "cost": 240,
                "flags": {
                    "Events": true,
                    "Market": true,
                    "P2P": true,
                    "Secure": true,
                    "Store": true,
                    "count_in_map": 1,
                    "deloot": 0
                },
                "lifetime": 14400,
                "min": 0,
                "nominal": 0,
                "quantmax": -1,
                "quantmin": -1,
                "restock": 1800,
                "tier": 4,
                "value": 240,
                "variants": {}
            }
        },
        "Lights": {
            "Chemlight_Red": {
                "cost": 240,
                "flags": {
                    "Events": true,
                    "Market": true,
                    "P2P": true,
                    "Secure": true,
                    "Store": true,
                    "count_in_map": 1,
                    "deloot": 0
                },
                "lifetime": 14400,
                "min": 0,
                "nominal": 0,
                "quantmax": -1,
                "quantmin": -1,
                "restock": 1800,
                "tier": 4,
                "value": 240,
                "variants": {
                    "Chemlight_Blue": {},
                    "Chemlight_Green": {},
                    "Chemlight_White": {},
                    "Chemlight_Yellow": {}
                }
            }
        }
    }
}